async_supercell_api/__init__.py
async_supercell_api/errors.py
async_supercell_api/types.py
async_supercell_api-0.0.1.dist-info/METADATA
async_supercell_api-0.0.1.dist-info/WHEEL
async_supercell_api-0.0.1.dist-info/top_level.txt
async_supercell_api-0.0.1.dist-info/RECORD
